lcsh_mcp_server/__init__.py
lcsh_mcp_server/cli.py
lcsh_mcp_server/server.py
lcsh_mcp_server-0.1.0.dist-info/METADATA
lcsh_mcp_server-0.1.0.dist-info/WHEEL
lcsh_mcp_server-0.1.0.dist-info/entry_points.txt
lcsh_mcp_server-0.1.0.dist-info/licenses/LICENSE
lcsh_mcp_server-0.1.0.dist-info/RECORD
