Metadata-Version: 2.4
Name: lcsh-mcp-server
Version: 0.1.0
Summary: A Model Context Protocol (MCP) server for Library of Congress Subject Headings
Project-URL: Homepage, https://github.com/yourusername/lcsh-mcp-server
Project-URL: Bug Tracker, https://github.com/yourusername/lcsh-mcp-server/issues
Project-URL: Documentation, https://github.com/yourusername/lcsh-mcp-server#readme
Author-email: KL Tang <tklpsu@gmail.com>
License-Expression: MIT
License-File: LICENSE
Classifier: Development Status :: 4 - Beta
Classifier: Intended Audience :: Developers
Classifier: License :: OSI Approved :: MIT License
Classifier: Programming Language :: Python :: 3
Classifier: Programming Language :: Python :: 3.12
Classifier: Topic :: Software Development :: Libraries :: Python Modules
Classifier: Topic :: Text Processing :: Linguistic
Requires-Python: >=3.12
Requires-Dist: mcp[cli]>=1.6.0
Requires-Dist: requests>=2.32.3
Requires-Dist: uvicorn>=0.27.0
